eta_mistral/__init__.py
eta_mistral/backend/input/eta_production_week/eta_production_week.csv
eta_mistral/backend/input/eta_production_week/three_linked_net_434.json
eta_mistral/backend/input/eta_production_week/three_linked_net_764.json
eta_mistral/backend/input/eta_production_week/three_sep_net_434.json
eta_mistral/backend/input/eta_production_week/three_sep_net_764.json
eta_mistral/backend/input/eta_production_week/two_linked_net_434.json
eta_mistral/backend/input/eta_production_week/two_linked_net_764.json
eta_mistral/backend/input/eta_production_week/two_sep_net_434.json
eta_mistral/backend/input/eta_production_week/two_sep_net_764.json
eta_mistral/backend/optimization/__init__.py
eta_mistral/backend/optimization/mistral_optimizer.py
eta_mistral/backend/plotting/energy_profile_potter.py
eta_mistral/backend/plotting/topology_plotter_straight.py
eta_mistral/backend/simulation/__init__.py
eta_mistral/backend/simulation/fmu/buffer_storage.fmu
eta_mistral/backend/simulation/fmu/cold_utility.fmu
eta_mistral/backend/simulation/fmu/hot_utility.fmu
eta_mistral/backend/simulation/fmu/Sink.fmu
eta_mistral/backend/simulation/fmu/Source.fmu
eta_mistral/backend/simulation/fmu/updated fmu.txt
eta_mistral/backend/simulation/simulator.py
eta_mistral/frontend/__init__.py
eta_mistral/frontend/assets/BMWe-Logo.png
eta_mistral/frontend/assets/Discrete_Optimization-Logo.png
eta_mistral/frontend/assets/ETA-Logo.png
eta_mistral/frontend/assets/GFAI-Logo.png
eta_mistral/frontend/assets/MISTRAL-Logo-color-rgb.png
eta_mistral/frontend/assets/ptj-Logo.png
eta_mistral/frontend/cli_app.py
eta_mistral/main.py
eta_mistral-0.0.4.dist-info/LICENSE
eta_mistral-0.0.4.dist-info/METADATA
eta_mistral-0.0.4.dist-info/WHEEL
eta_mistral-0.0.4.dist-info/RECORD
